tinyoffice/__init__.py
tinyoffice/__main__.py
tinyoffice/tinyoffice.py
tinyoffice-0.0.9.dist-info/licenses/LICENSE
tinyoffice-0.0.9.dist-info/METADATA
tinyoffice-0.0.9.dist-info/WHEEL
tinyoffice-0.0.9.dist-info/top_level.txt
tinyoffice-0.0.9.dist-info/RECORD
