Metadata-Version: 2.4
Name: tinyoffice
Version: 0.0.9
Summary: Make your Office files tiny!
Author-email: Samuel Woodward <sam@woodward.fyi>
Project-URL: Homepage, https://github.com/PyWoody/tinyoffice
Keywords: office,compress,convert,image,Word,Excel,Powerpoint
Classifier: Programming Language :: Python :: 3
Classifier: License :: OSI Approved :: MIT License
Classifier: Operating System :: OS Independent
Requires-Python: >=3.9
License-File: LICENSE
Requires-Dist: Pillow
Dynamic: license-file
